findany_beta/__init__.py
findany_beta/findany_wrapper.py
findany_beta/bin/findany
findany_beta/bin/findany.exe
findany_beta-0.0.4.dist-info/METADATA
findany_beta-0.0.4.dist-info/WHEEL
findany_beta-0.0.4.dist-info/entry_points.txt
findany_beta-0.0.4.dist-info/top_level.txt
findany_beta-0.0.4.dist-info/RECORD
