Metadata-Version: 2.4
Name: findany_beta
Version: 0.0.4
Summary: A command line tool for searching multiple substrings in a multiline text file
Author-email: Igor Belousov <imbelousov66@gmail.com>
Project-URL: Homepage, https://github.com/imbelousov/findany
Project-URL: Repository, https://github.com/imbelousov/findany
Project-URL: Issues, https://github.com/imbelousov/findany/issues
Classifier: Programming Language :: Python :: 3
Classifier: Programming Language :: C
Classifier: Operating System :: OS Independent
Requires-Python: >=3.9
